beet/__init__.py
beet/__main__.py
beet/contrib/__init__.py
beet/contrib/auto_yaml.py
beet/contrib/autosave.py
beet/contrib/babelbox.py
beet/contrib/cleanup_overlays.py
beet/contrib/clear.py
beet/contrib/copy_files.py
beet/contrib/dbg.py
beet/contrib/default.py
beet/contrib/dundervar.py
beet/contrib/error_message.py
beet/contrib/extra_files.py
beet/contrib/find_replace.py
beet/contrib/format_json.py
beet/contrib/function_header.py
beet/contrib/hangman.py
beet/contrib/inline_function.py
beet/contrib/inline_function_tag.py
beet/contrib/installation_advancement.py
beet/contrib/json_log.py
beet/contrib/json_reporter.py
beet/contrib/lantern_load.py
beet/contrib/line_endings.py
beet/contrib/link.py
beet/contrib/livereload.py
beet/contrib/load.py
beet/contrib/load_yaml.py
beet/contrib/log_level.py
beet/contrib/messages.py
beet/contrib/minify_function.py
beet/contrib/minify_json.py
beet/contrib/model_merging.py
beet/contrib/optifine.py
beet/contrib/output.py
beet/contrib/relative_function_path.py
beet/contrib/rename_files.py
beet/contrib/render.py
beet/contrib/sandstone.py
beet/contrib/scoreboard.py
beet/contrib/stdin.py
beet/contrib/strip_final_newlines.py
beet/contrib/template_context.py
beet/contrib/template_sandbox.py
beet/contrib/text_encoding.py
beet/contrib/unknown_files.py
beet/contrib/vanilla.py
beet/contrib/worldgen.py
beet/contrib/yellow_shulker_box.py
beet/core/__init__.py
beet/core/cache.py
beet/core/container.py
beet/core/error.py
beet/core/file.py
beet/core/utils.py
beet/core/watch.py
beet/library/__init__.py
beet/library/base.py
beet/library/data_pack.py
beet/library/resource_pack.py
beet/library/test_utils.py
beet/library/utils.py
beet/preset_stdin.yml
beet/py.typed
beet/pytest_plugin.py
beet/resources/__init__.py
beet/resources/pack_format_registry.json
beet/resources/pack_format_registry.py
beet/toolchain/__init__.py
beet/toolchain/cli.py
beet/toolchain/commands.py
beet/toolchain/config.py
beet/toolchain/context.py
beet/toolchain/generator.py
beet-0.113.0.dist-info/licenses/LICENSE
beet-0.113.0.dist-info/WHEEL
beet-0.113.0.dist-info/entry_points.txt
beet-0.113.0.dist-info/METADATA
beet-0.113.0.dist-info/RECORD
