Metadata-Version: 2.4
Name: beet
Version: 0.113.0
Summary: The Minecraft pack development kit
Keywords: beet,minecraft,datapack,resourcepack,mcfunction
Author: Valentin Berlier
Author-email: Valentin Berlier <berlier.v@gmail.com>
License-Expression: MIT
License-File: LICENSE
Requires-Dist: click>=8.3.1
Requires-Dist: click-help-colors>=0.9.4
Requires-Dist: jinja2>=3.1.6
Requires-Dist: nbtlib==1.12.1
Requires-Dist: pathspec>=0.12.1
Requires-Dist: pillow>=12.0.0
Requires-Dist: pydantic>=2.12.4
Requires-Dist: pyyaml>=6.0.3
Requires-Dist: toml>=0.10.2
Requires-Python: >=3.14
Project-URL: Repository, https://github.com/mcbeet/beet
